<rspec xmlns:xsi="http://www.w3.org/2001/XMLSchema-instance" xmlns="http://www.protogeni.net/resources/rspec/2" xmlns:pxe="http://www.protogeni.net/resources/rspec/ext/pxe/1" xsi:schemaLocation="http://www.protogeni.net/resources/rspec/2 http://www.protogeni.net/resources/rspec/2/ad.xsd http://www.protogeni.net/resources/rspec/ext/pxe/1 ad.xsd" type="advertisement" generated="2012-03-06T02:09:23Z" expires="2012-03-06T02:09:23Z" >

<node component_manager_id="urn:publicid:IDN+emulab.net+authority+cm" component_name="pc102"  component_id="urn:publicid:IDN+emulab.net+node+pc102"  exclusive="true" >
  <hardware_type name="pc850" />
  <sliver_type name="raw-pc" />
  <available now="true" />
  <location country="US" longitude="-111.84581" latitude="40.768652" />
  <services>
    <pxe:services_pxe_boot name="boot_image.img" />
  </services>
</node>

</rspec>
